samp_py/__init__.py
samp_py/client.py
samp_py/constants.py
samp_py/exceptions.py
samp_py/models.py
samp_py/utils.py
samp_python-1.0.0.dist-info/METADATA
samp_python-1.0.0.dist-info/WHEEL
samp_python-1.0.0.dist-info/top_level.txt
samp_python-1.0.0.dist-info/RECORD
