Metadata-Version: 2.1
Name: samp-python
Version: 1.0.0
Summary: SA:MP API client for Python
Home-page: https://github.com/enginestein/SAMP.py
Author: Arya Praneil Pritesh
Author-email: aryapraneil@gmail.com
License: GPL-3.0-only
Project-URL: Source, https://github.com/enginestein/SAMP.py
Project-URL: Tracker, https://github.com/enginestein/SAMP.py
Classifier: Development Status :: 5 - Production/Stable
Classifier: Programming Language :: Python :: 3 :: Only
Classifier: Programming Language :: Python :: 3
Classifier: Programming Language :: Python :: 3.6
Classifier: Programming Language :: Python :: 3.7
Classifier: Programming Language :: Python :: 3.8
Classifier: Programming Language :: Python :: 3.9
Classifier: Programming Language :: Python :: 3.10
Classifier: Environment :: Console
Classifier: Intended Audience :: Developers
Classifier: Natural Language :: English
Classifier: Operating System :: OS Independent
